aggimg.py
aggimg-0.0.2.dist-info/LICENSE
aggimg-0.0.2.dist-info/METADATA
aggimg-0.0.2.dist-info/WHEEL
aggimg-0.0.2.dist-info/entry_points.txt
aggimg-0.0.2.dist-info/top_level.txt
aggimg-0.0.2.dist-info/RECORD
