Metadata-Version: 2.1
Name: aggimg
Version: 0.0.2
Summary: Aggressive image optimizer cli!
Home-page: https://github.com/ClimenteA/aggressive-image-optimizer-cli
Author: Climente Alin
Author-email: climente.alin@gmail.com
License: MIT
License-File: LICENSE
Requires-Dist: pillow ==10.3.0
